{
  "api": {
    "quiz": {
      "service": "AppSync",
      "providerPlugin": "awscloudformation",
      "output": {
        "authConfig": {
          "defaultAuthentication": {
            "authenticationType": "API_KEY",
            "apiKeyConfig": {
              "apiKeyExpirationDays": 365,
              "apiKeyExpirationDate": "2022-12-30T13:51:52.234Z",
              "description": "quiz API key"
            }
          },
          "additionalAuthenticationProviders": [
            {
              "authenticationType": "AWS_IAM"
            }
          ]
        }
      }
    }
  }
}