{
  "version": 1,
  "serviceConfiguration": {
    "apiName": "quiz",
    "serviceName": "AppSync",
    "gqlSchemaPath": "C:\\Users\\andre\\Documents\\Projekte\\GitHub\\quiz\\amplify\\backend\\api\\quiz\\schema.graphql",
    "defaultAuthType": {
      "mode": "API_KEY",
      "expirationTime": 365,
      "apiKeyExpirationDate": "2022-12-30T13:51:52.234Z",
      "keyDescription": "quiz API key"
    },
    "additionalAuthTypes": [
      {
        "mode": "AWS_IAM"
      }
    ],
    "conflictResolution": {
      "defaultResolutionStrategy": {
        "type": "AUTOMERGE"
      }
    }
  }
}